hsclient/__init__.py
hsclient/hydroshare.py
hsclient/json_models.py
hsclient/oauth2_model.py
hsclient/utils.py
hsclient-1.1.6.dist-info/LICENSE.txt
hsclient-1.1.6.dist-info/METADATA
hsclient-1.1.6.dist-info/WHEEL
hsclient-1.1.6.dist-info/top_level.txt
hsclient-1.1.6.dist-info/RECORD
