Metadata-Version: 2.2
Name: hsclient
Version: 1.1.6
Summary: A python client for managing HydroShare resources
Home-page: https://github.com/hydroshare/hsclient
Author: Scott Black
Author-email: scott.black@usu.edu
License: MIT
Classifier: Programming Language :: Python :: 3
Classifier: Programming Language :: Python :: 3.6
Classifier: Programming Language :: Python :: 3.7
Classifier: Programming Language :: Python :: 3.8
Classifier: Programming Language :: Python :: 3.9
Requires-Python: >=3.9
License-File: LICENSE.txt
Requires-Dist: hsmodels>=1.0.4
Requires-Dist: requests
Requires-Dist: requests_oauthlib
Requires-Dist: setuptools
Provides-Extra: pandas
Requires-Dist: pandas; extra == "pandas"
Provides-Extra: xarray
Requires-Dist: netCDF4; extra == "xarray"
Requires-Dist: xarray; extra == "xarray"
Provides-Extra: rasterio
Requires-Dist: rasterio; extra == "rasterio"
Provides-Extra: fiona
Requires-Dist: fiona; extra == "fiona"
Provides-Extra: all
Requires-Dist: pandas; extra == "all"
Requires-Dist: netCDF4; extra == "all"
Requires-Dist: xarray; extra == "all"
Requires-Dist: rasterio; extra == "all"
Requires-Dist: fiona; extra == "all"
Provides-Extra: dev
Requires-Dist: pandas; extra == "dev"
Requires-Dist: netCDF4; extra == "dev"
Requires-Dist: xarray; extra == "dev"
Requires-Dist: rasterio; extra == "dev"
Requires-Dist: fiona; extra == "dev"
Requires-Dist: pytest; extra == "dev"
Requires-Dist: pytest-xdist; extra == "dev"
Requires-Dist: pytest-cov; extra == "dev"
Requires-Dist: mkdocs; extra == "dev"
Requires-Dist: mknotebooks; extra == "dev"
Requires-Dist: mkdocstrings; extra == "dev"
Requires-Dist: mkdocstrings-python; extra == "dev"
Dynamic: author
Dynamic: author-email
Dynamic: classifier
Dynamic: description
Dynamic: description-content-type
Dynamic: home-page
Dynamic: license
Dynamic: provides-extra
Dynamic: requires-dist
Dynamic: requires-python
Dynamic: summary
